press/__init__.py
press/entry.py
press/exceptions.py
press/log.py
press/plugin_init.py
press/press.py
press/press_cli.py
press/configuration/__init__.py
press/configuration/global_defaults.py
press/configuration/util.py
press/generators/__init__.py
press/generators/chroot.py
press/generators/image.py
press/generators/layout.py
press/generators/post_target.py
press/helpers/__init__.py
press/helpers/cli.py
press/helpers/deployment.py
press/helpers/download.py
press/helpers/imagefile.py
press/helpers/kexec.py
press/helpers/lvm.py
press/helpers/mdadm.py
press/helpers/networking.py
press/helpers/package.py
press/helpers/parted.py
press/helpers/sysfs_info.py
press/helpers/udev.py
press/hooks/__init__.py
press/hooks/hooks.py
press/layout/__init__.py
press/layout/disk.py
press/layout/fstab.py
press/layout/layout.py
press/layout/lvm.py
press/layout/raid.py
press/layout/filesystems/__init__.py
press/layout/filesystems/extended.py
press/layout/filesystems/fat.py
press/layout/filesystems/ntfs.py
press/layout/filesystems/swap.py
press/layout/filesystems/xfs.py
press/models/__init__.py
press/models/lvm.py
press/models/partition.py
press/plugins/__init__.py
press/plugins/example.py
press/targets/__init__.py
press/targets/registration.py
press/targets/target_base.py
press/targets/linux/__init__.py
press/targets/linux/grub2_debian_target.py
press/targets/linux/grub2_target.py
press/targets/linux/grub_target.py
press/targets/linux/linux_target.py
press/targets/linux/debian/__init__.py
press/targets/linux/debian/debian_target.py
press/targets/linux/debian/debian_8/__init__.py
press/targets/linux/debian/debian_8/debian_8_target.py
press/targets/linux/debian/debian_9/__init__.py
press/targets/linux/debian/debian_9/debian_9_target.py
press/targets/linux/debian/networking/__init__.py
press/targets/linux/debian/networking/debian_networking.py
press/targets/linux/debian/networking/interfaces_template.py
press/targets/linux/debian/networking/netplan_template.py
press-0.5.8.dist-info/METADATA
press-0.5.8.dist-info/WHEEL
press-0.5.8.dist-info/entry_points.txt
press-0.5.8.dist-info/pbr.json
press-0.5.8.dist-info/top_level.txt
press-0.5.8.dist-info/RECORD
