Metadata-Version: 1.0
Name: press
Version: 0.5.8
Summary: An OS image installer that supports custome partitioning, lvm, and software raid
Home-page: http://github.com/jr0d/press
Author: Jared Rodriguez
Author-email: jared.rodriguez@rackspace.com
License: GPLv2
Platform: UNKNOWN
